{"type":"FeatureCollection","features":[{"type":"Feature","properties":{"marker-color":"#7E7E7E","marker-size":"medium","marker-symbol":"","Name":"Home"},"geometry":{"type":"Point","coordinates":[-87.72552967071533,42.03532512806467]}},{"type":"Feature","properties":{},"geometry":{"type":"Point","coordinates":[-87.72557258605957,42.03342059185603]}},{"type":"Feature","properties":{},"geometry":{"type":"Point","coordinates":[-87.74728775024412,42.033165586859894]}},{"type":"Feature","properties":{},"geometry":{"type":"Point","coordinates":[-87.74711608886719,42.040624060291336]}},{"type":"Feature","properties":{},"geometry":{"type":"Point","coordinates":[-87.74703025817871,42.0479541854152]}},{"type":"Feature","properties":{"marker-color":"#7E7E7E","marker-size":"medium","marker-symbol":"","Name":"Old Orchard Mall"},"geometry":{"type":"Point","coordinates":[-87.74681568145752,42.055187870981904]}}]}